tomi_kristof_package_test/__init__.py
tomi_kristof_package_test/core.py
tomi_kristof_package_test-0.1.2.dist-info/METADATA
tomi_kristof_package_test-0.1.2.dist-info/WHEEL
tomi_kristof_package_test-0.1.2.dist-info/RECORD
