Metadata-Version: 2.3
Name: tomi-kristof-package-test
Version: 0.1.2
Summary: 
Author: Kristof Menyhert
Author-email: menyhert.kristof@gmail.com
Requires-Python: >=3.10
Classifier: Programming Language :: Python :: 3
Classifier: Programming Language :: Python :: 3.10
Classifier: Programming Language :: Python :: 3.11
Classifier: Programming Language :: Python :: 3.12
Classifier: Programming Language :: Python :: 3.13
Requires-Dist: pandas (>=2.2.3,<3.0.0)
Requires-Dist: pytest (>=8.3.5,<9.0.0)
